<annotation>
	<folder>train</folder>
	<filename>Suji-Ke-Modak-FI.jpg</filename>
	<path>C:\Tensorflow1\models\research\object_detection\images\train\Suji-Ke-Modak-FI.jpg</path>
	<source>
		<database>Unknown</database>
	</source>
	<size>
		<width>1280</width>
		<height>720</height>
		<depth>3</depth>
	</size>
	<segmented>0</segmented>
	<object>
		<name>modak</name>
		<pose>Unspecified</pose>
		<truncated>0</truncated>
		<difficult>0</difficult>
		<bndbox>
			<xmin>557</xmin>
			<ymin>237</ymin>
			<xmax>815</xmax>
			<ymax>576</ymax>
		</bndbox>
	</object>
	<object>
		<name>modak</name>
		<pose>Unspecified</pose>
		<truncated>0</truncated>
		<difficult>0</difficult>
		<bndbox>
			<xmin>880</xmin>
			<ymin>128</ymin>
			<xmax>1127</xmax>
			<ymax>418</ymax>
		</bndbox>
	</object>
	<object>
		<name>modak</name>
		<pose>Unspecified</pose>
		<truncated>0</truncated>
		<difficult>0</difficult>
		<bndbox>
			<xmin>320</xmin>
			<ymin>177</ymin>
			<xmax>570</xmax>
			<ymax>433</ymax>
		</bndbox>
	</object>
</annotation>
